omigami/__init__.py
omigami/_version.py
omigami/config.py
omigami/config_default.yaml
omigami/endpoint.py
omigami/ms2deepscore.py
omigami/plotting.py
omigami/spec2vec.py
omigami-0.1.8.dist-info/LICENSE
omigami-0.1.8.dist-info/METADATA
omigami-0.1.8.dist-info/WHEEL
omigami-0.1.8.dist-info/entry_points.txt
omigami-0.1.8.dist-info/top_level.txt
omigami-0.1.8.dist-info/RECORD
